README
setup.py
Eve_ElasticSearch.egg-info/PKG-INFO
Eve_ElasticSearch.egg-info/SOURCES.txt
Eve_ElasticSearch.egg-info/dependency_links.txt
Eve_ElasticSearch.egg-info/requires.txt
Eve_ElasticSearch.egg-info/top_level.txt
eve_es/__init__.py
eve_es/elastic.py
eve_es/validation.py